{"flow":[{"id":1,"mapper":{"team":80,"limit":"10","folder":1864,"islinked":false,"organization":658333},"module":"make:searchScenarios","version":1,"metadata":{"expect":[{"name":"organization","type":"select","label":"Organization"},{"name":"islinked","type":"boolean","label":"Only active scenarios"},{"name":"limit","type":"uinteger","label":"Limit"},{"name":"team","type":"select","label":"Team"},{"name":"defaultProperties","type":"filter","label":"Filter by default scenario properties","options":{"logic":"and","store":[{"label":"Created by user name (Text)","value":"createdByUserName"},{"label":"Last edited by user name (Text)","value":"updatedByUserName"},{"label":"Scenario ID (Number)","value":"id"},{"label":"Incomplete executions (Number)","value":"incompleteExecutions"}],"operators":[{"label":"Text","options":[{"label":"Contains","value":"contains"}]},{"label":"Number","options":[{"label":"Equals","value":"equals"}]}]}},{"name":"customProperties","type":"filter","label":"Filter by custom scenario properties","options":{"logic":"and","store":[{"label":"[AUTOMATED] Auto-generated ID Atlassian Confluence (number)","value":"ScenarioStandardIDAtlassianConfluence"},{"label":"[AUTOMATED] Auto-generated scenario description (longText)","value":"ScenarioStandardDescription"},{"label":"[AUTOMATED] Auto-generated scenario documentation URL (shortText)","value":"ScenarioStandardDocumentationURL"},{"label":"[AUTOMATED] Scenario name based on naming conventions (shortText)","value":"ScenarioStandardName"},{"label":"[AUTOMATED] Weight Score for Scenario Optimisation (shortText)","value":"WeightScore"},{"label":"isTest (boolean)","value":"isTest"},{"label":"isCritical (boolean)","value":"isCritical"},{"label":"Backup (shortText)","value":"BackupOfScenario"},{"label":"Description (longText)","value":"Description"},{"label":"Project (shortText)","value":"Project"},{"label":"Status (dropdown)","value":"Status"},{"label":"Sub Team (longText)","value":"SubTeam"},{"label":"Documentation URL (longText)","value":"DocumentationURL"},{"label":"Owner (shortText)","value":"OwnerOfScenario"}],"operators":[{"label":"Text","options":[{"label":"Contains","value":"text:contains"}]},{"label":"Number","options":[{"label":"Equals","value":"number:equals"}]},{"label":"Boolean","options":[{"label":"Equals","value":"boolean:equals"}]},{"label":"Dropdown","options":[{"label":"Equals","value":"dropdown:equals"}]},{"label":"Multiselect","options":[{"label":"Equals","value":"multiselect:equals"}]}]}},{"name":"folder","type":"select","label":"Folder"}],"restore":{"expect":{"team":{"mode":"chose","label":"SALES_VE_GTM_Test & QA"},"folder":{"mode":"chose","label":"Mark Demos"},"islinked":{"mode":"chose"},"organization":{"mode":"chose","label":"🔥_Make_Global_ORG_🔥"}},"parameters":{"__IMTCONN__":{"data":{"scoped":"true","connection":"make"},"label":"My Make (API key) connection (j.vanmaanen.ext@celonis.de)"}}},"designer":{"x":0,"y":0},"parameters":[{"name":"__IMTCONN__","type":"account:make2,make","label":"Connection","required":true}]},"parameters":{"__IMTCONN__":8149}},{"id":5,"mapper":null,"module":"builtin:BasicRouter","routes":[{"flow":[{"id":7,"mapper":{"select":"file","scenario":"{{1.id}}"},"module":"make:getAScenarioBlueprint","version":1,"metadata":{"expect":[{"name":"scenario","type":"text","label":"Scenario ID","required":true},{"name":"draft","type":"boolean","label":"Draft"},{"name":"select","type":"select","label":"Return a blueprint","required":true,"validate":{"enum":["json","string","file"]}}],"restore":{"expect":{"draft":{"mode":"chose"},"select":{"mode":"chose","label":"In a JSON file"}},"parameters":{"__IMTCONN__":{"data":{"scoped":"true","connection":"make"},"label":"My Make (API key) connection (j.vanmaanen.ext@celonis.de)"}}},"designer":{"x":600,"y":0},"interface":[{"name":"blueprint","type":"buffer","label":"Blueprint data","semantic":"file:data"},{"name":"filename","type":"filename","label":"File name","semantic":"file:name"},{"name":"gitSHA","type":"text","label":"GitHub SHA"},{"name":"scheduling","spec":[{"name":"type","type":"text","label":"Type"},{"name":"between","spec":{"type":"date"},"type":"array","label":"Between"},{"name":"interval","type":"number","label":"Interval"},{"name":"restrict","spec":{"spec":[{"name":"days","spec":{"type":"number"},"type":"array","label":"Days"},{"name":"time","spec":{"type":"text"},"type":"array","label":"Time"},{"name":"months","spec":{"type":"number"},"type":"array","label":"Months"}],"type":"collection"},"type":"array","label":"Restrict"},{"name":"date","time":true,"type":"date","label":"Date"},{"name":"time","type":"text","label":"Time"},{"name":"days","type":"array","label":"Days"},{"name":"months","type":"array","label":"Months"}],"type":"collection","label":"Scheduling"},{"name":"concept","type":"boolean","label":"Concept"},{"name":"idSequence","type":"uinteger","label":"ID Sequence"},{"name":"created","time":true,"type":"date","label":"Created"},{"name":"last_edit","time":true,"type":"date","label":"Last edit"},{"name":"metadata","spec":[{"name":"input_spec","type":"any","label":"Input spec"},{"name":"output_spec","type":"any","label":"Output spec"}],"type":"collection","label":"Metadata"},{"name":"length","type":"number","label":"Length"}],"parameters":[{"name":"__IMTCONN__","type":"account:make2,make","label":"Connection","required":true}]},"parameters":{"__IMTCONN__":8149}},{"id":9,"mapper":{"path":"{{1.id}}_{{1.name}}.json","contents":"{{base64(7.blueprint)}}"},"module":"json:AggregateToJSON","version":1,"metadata":{"expect":[{"name":"path","type":"text","label":"Path"},{"name":"contents","type":"text","label":"Contents"}],"restore":{"extra":{"feeder":{"label":"Make - Search scenarios [1]"}},"parameters":{"type":{"label":"GitCommit"},"space":{"label":"Empty"}}},"designer":{"x":900,"y":0},"parameters":[{"name":"type","type":"udt","label":"Data structure","required":true},{"name":"space","type":"select","label":"Indentation","validate":{"enum":["tab","2","4"]}}]},"parameters":{"type":2706,"space":"","feeder":1}},{"id":4,"mapper":{"method":"POST","queryBody":"{\n  repository(name: \"make_scenarios\", owner: \"makeskinner\") {\n    defaultBranchRef {\n      target {\n        ... on Commit {\n          oid\n          commitUrl\n        }\n      }\n    }\n  }\n}","variablesDataSource":"array"},"module":"github:makeAnAPICall","version":4,"metadata":{"expect":[{"name":"method","type":"select","label":"Method","required":true,"validate":{"enum":["GET","POST"]}},{"name":"queryBody","type":"text","label":"Query","required":true},{"name":"operationName","type":"text","label":"Operation name"},{"name":"variablesDataSource","type":"select","label":"Variables data source","required":true,"validate":{"enum":["array","object"]}},{"name":"variables","spec":[{"name":"key","type":"text","label":"Key"},{"name":"value","type":"text","label":"Value"}],"type":"array","label":"Variables"}],"restore":{"expect":{"method":{"mode":"chose","label":"POST (queries and mutations)"},"variables":{"mode":"chose"},"variablesDataSource":{"mode":"chose","label":"Form"}},"parameters":{"__IMTCONN__":{"data":{"scoped":"true","connection":"github"},"label":"Marks GitHub OAuth connection (makeskinner)"}}},"designer":{"x":1200,"y":0,"name":"Get Latest SHA"},"parameters":[{"name":"__IMTCONN__","type":"account:github2,github","label":"Connection","required":true}]},"parameters":{"__IMTCONN__":11869}},{"id":6,"mapper":{"method":"POST","queryBody":"mutation ($input: CreateCommitOnBranchInput!) {\n  createCommitOnBranch(input: $input) {\n    commit { url }\n  }\n}","variables":"{\n  \"input\": {\n    \"branch\": {\n      \"repositoryNameWithOwner\": \"makeskinner/make_scenarios\",\n      \"branchName\": \"main\"\n    },\n    \"message\": {\n      \"headline\": \"Bulk Backup of Scenarios\"\n    },\n    \"fileChanges\": {\n      \"additions\": {{9.json}}\n    },\n    \"expectedHeadOid\": \"{{4.body.data.repository.defaultBranchRef.target.oid}}\"\n  }\n}","variablesDataSource":"object"},"module":"github:makeAnAPICall","version":4,"metadata":{"expect":[{"name":"method","type":"select","label":"Method","required":true,"validate":{"enum":["GET","POST"]}},{"name":"queryBody","type":"text","label":"Query","required":true},{"name":"operationName","type":"text","label":"Operation name"},{"name":"variablesDataSource","type":"select","label":"Variables data source","required":true,"validate":{"enum":["array","object"]}},{"name":"variables","type":"any","label":"Variables"}],"restore":{"expect":{"method":{"mode":"chose","label":"POST (queries and mutations)"},"variablesDataSource":{"mode":"chose","label":"Collection"}},"parameters":{"__IMTCONN__":{"data":{"scoped":"true","connection":"github"},"label":"Marks GitHub OAuth connection (makeskinner)"}}},"advanced":true,"designer":{"x":1500,"y":0},"parameters":[{"name":"__IMTCONN__","type":"account:github2,github","label":"Connection","required":true}]},"parameters":{"__IMTCONN__":11869}}]}],"version":1,"metadata":{"designer":{"x":300,"y":0}}}],"name":"Integration Make","metadata":{"instant":false,"version":1,"designer":{"orphans":[],"samples":{"1":{"id":28309,"name":"Blueprinter","hookId":null,"teamId":80,"created":"2025-12-15T16:50:03.251Z","deviceId":null,"dlqCount":0,"folderId":1864,"isPaused":false,"islinked":false,"islocked":false,"lastEdit":"2025-12-16T11:54:27.713Z","nextExec":null,"isinvalid":false,"iswaiting":false,"scheduling":{"type":"indefinitely","interval":900},"description":"","deviceScope":null,"__IMTINDEX__":1,"usedPackages":["confluence"],"__IMTLENGTH__":6,"createdByUser":{"id":1519946,"name":"GTM SE Demo","email":"gtm-se-demo@make.com"},"updatedByUser":{"id":930790,"name":"Mark Skinner","email":"m.skinner@make.com"},"customProperties":null},"4":{"body":{"data":{"repository":{"defaultBranchRef":{"target":{"oid":"279dec51ad4ef553fe90b1c0705640727f322e2e","commitUrl":"https://github.com/makeskinner/make_scenarios/commit/279dec51ad4ef553fe90b1c0705640727f322e2e"}}}}},"headers":{"date":"Tue, 16 Dec 2025 13:40:45 GMT","vary":"Accept-Encoding, Accept, X-Requested-With","server":"github.com","connection":"close","content-type":"application/json; charset=utf-8","content-length":"214","x-oauth-scopes":"read:user, repo","referrer-policy":"origin-when-cross-origin, strict-origin-when-cross-origin","x-frame-options":"deny","x-ratelimit-used":"9","x-xss-protection":"0","x-oauth-client-id":"9e5b3e0ad15e729a3a18","x-ratelimit-limit":"5000","x-ratelimit-reset":"1765895142","x-github-media-type":"github.v4; format=json","x-github-request-id":"6D2D:1D8819:718A77:8BECDE:6941615D","x-ratelimit-resource":"graphql","x-ratelimit-remaining":"5000","x-content-type-options":"nosniff","content-security-policy":"default-src 'none'","x-accepted-oauth-scopes":"repo","strict-transport-security":"max-age=31536000; includeSubdomains; preload","access-control-allow-origin":"*","access-control-expose-headers":"ETag, Link, Location, Retry-After, X-GitHub-OTP, X-RateLimit-Limit, X-RateLimit-Remaining, X-RateLim..."},"statusCode":200},"6":{"body":{"data":{"createCommitOnBranch":{"commit":{"url":"https://github.com/makeskinner/make_scenarios/commit/ddc6b39ec8074c7919d25aa3fc9ba45f209b8138"}}}},"headers":{"date":"Tue, 16 Dec 2025 13:40:46 GMT","vary":"Accept-Encoding, Accept, X-Requested-With","server":"github.com","connection":"close","content-type":"application/json; charset=utf-8","content-length":"148","x-oauth-scopes":"read:user, repo","referrer-policy":"origin-when-cross-origin, strict-origin-when-cross-origin","x-frame-options":"deny","x-ratelimit-used":"10","x-xss-protection":"0","x-oauth-client-id":"9e5b3e0ad15e729a3a18","x-ratelimit-limit":"5000","x-ratelimit-reset":"1765895142","x-github-media-type":"github.v4; format=json","x-github-request-id":"73EA:1F8FCE:6F8CD8:89ED7E:6941615E","x-ratelimit-resource":"graphql","x-ratelimit-remaining":"5000","x-content-type-options":"nosniff","content-security-policy":"default-src 'none'","x-accepted-oauth-scopes":"repo","strict-transport-security":"max-age=31536000; includeSubdomains; preload","access-control-allow-origin":"*","access-control-expose-headers":"ETag, Link, Location, Retry-After, X-GitHub-OTP, X-RateLimit-Limit, X-RateLimit-Remaining, X-RateLim..."},"statusCode":200},"7":{"gitSHA":"2821b956629406617baab685be9341a641d97116","length":18403,"concept":false,"created":"2025-12-15T16:50:03.251Z","filename":"blueprint.json","metadata":{"input_spec":[],"output_spec":[]},"blueprint":"IMTBuffer(18403, binary, b1d21bf2d3e458d1d014a98b2f13d76c3cbae5fd): 7b22666c6f77223a5b7b226964223a31...","last_edit":"2025-12-16T11:54:27.713Z","idSequence":13,"scheduling":{"type":"indefinitely","interval":900}},"9":{"json":"[{\"path\":\"28309_Blueprinter.json\",\"contents\":\"eyJmbG93IjpbeyJpZCI6MSwibWFwcGVyIjp7ImlkIjoiMjUwODg4MT..."}}},"scenario":{"dlq":false,"slots":null,"dataloss":false,"maxErrors":3,"autoCommit":true,"roundtrips":1,"sequential":false,"confidential":false,"freshVariables":false,"autoCommitTriggerLast":true}}}